cdetools/__init__.py
cdetools/cde_loss.py
cdetools/cdf_coverage.py
cdetools/hpd_contours.py
cdetools/hpd_coverage.py
cdetools-0.0.1.dist-info/LICENSE
cdetools-0.0.1.dist-info/METADATA
cdetools-0.0.1.dist-info/WHEEL
cdetools-0.0.1.dist-info/top_level.txt
cdetools-0.0.1.dist-info/RECORD
